PYvaporwave/_init_.py
PYvaporwave/image_bend/image_bender.py
PYvaporwave-2.0.0.dist-info/METADATA
PYvaporwave-2.0.0.dist-info/WHEEL
PYvaporwave-2.0.0.dist-info/top_level.txt
PYvaporwave-2.0.0.dist-info/RECORD
