Metadata-Version: 2.1
Name: PYvaporwave
Version: 2.0.0
Summary: A Vaporwave python library
Author-email: Yiannis Menexes <johnmenex@gmail.com>
Project-URL: Homepage, https://github.com/vaseelaser/PYvaporwave
Project-URL: Bug Tracker, https://github.com/vaseelaser/PYvaporwave/issues
Classifier: Programming Language :: Python :: 3
Classifier: License :: OSI Approved :: MIT License
Classifier: Operating System :: OS Independent
Requires-Python: >=3.7
Requires-Dist: numpy (~=1.23.4)
Requires-Dist: Pillow (~=9.2.0)
